[
  { "country": "Qatar", "code": "qa", "url": "https://flagcdn.com/w640/qa.png" },
  { "country": "Ecuador", "code": "ec", "url": "https://flagcdn.com/w640/ec.png" },
  { "country": "Senegal", "code": "sn", "url": "https://flagcdn.com/w640/sn.png" },
  { "country": "Netherlands", "code": "nl", "url": "https://flagcdn.com/w640/nl.png" },
  { "country": "England", "code": "gb-eng", "url": "https://flagcdn.com/w640/gb-eng.png" },
  { "country": "Iran", "code": "ir", "url": "https://flagcdn.com/w640/ir.png" },
  { "country": "USA", "code": "us", "url": "https://flagcdn.com/w640/us.png" },
  { "country": "Wales", "code": "gb-wls", "url": "https://flagcdn.com/w640/gb-wls.png" },
  { "country": "Argentina", "code": "ar", "url": "https://flagcdn.com/w640/ar.png" },
  { "country": "Saudi Arabia", "code": "sa", "url": "https://flagcdn.com/w640/sa.png" },
  { "country": "Mexico", "code": "mx", "url": "https://flagcdn.com/w640/mx.png" },
  { "country": "Poland", "code": "pl", "url": "https://flagcdn.com/w640/pl.png" },
  { "country": "France", "code": "fr", "url": "https://flagcdn.com/w640/fr.png" },
  { "country": "Australia", "code": "au", "url": "https://flagcdn.com/w640/au.png" },
  { "country": "Denmark", "code": "dk", "url": "https://flagcdn.com/w640/dk.png" },
  { "country": "Tunisia", "code": "tn", "url": "https://flagcdn.com/w640/tn.png" },
  { "country": "Spain", "code": "es", "url": "https://flagcdn.com/w640/es.png" },
  { "country": "Costa Rica", "code": "cr", "url": "https://flagcdn.com/w640/cr.png" },
  { "country": "Germany", "code": "de", "url": "https://flagcdn.com/w640/de.png" },
  { "country": "Japan", "code": "jp", "url": "https://flagcdn.com/w640/jp.png" },
  { "country": "Belgium", "code": "be", "url": "https://flagcdn.com/w640/be.png" },
  { "country": "Canada", "code": "ca", "url": "https://flagcdn.com/w640/ca.png" },
  { "country": "Morocco", "code": "ma", "url": "https://flagcdn.com/w640/ma.png" },
  { "country": "Croatia", "code": "hr", "url": "https://flagcdn.com/w640/hr.png" },
  { "country": "Brazil", "code": "br", "url": "https://flagcdn.com/w640/br.png" },
  { "country": "Serbia", "code": "rs", "url": "https://flagcdn.com/w640/rs.png" },
  { "country": "Switzerland", "code": "ch", "url": "https://flagcdn.com/w640/ch.png" },
  { "country": "Cameroon", "code": "cm", "url": "https://flagcdn.com/w640/cm.png" },
  { "country": "Portugal", "code": "pt", "url": "https://flagcdn.com/w640/pt.png" },
  { "country": "Ghana", "code": "gh", "url": "https://flagcdn.com/w640/gh.png" },
  { "country": "Uruguay", "code": "uy", "url": "https://flagcdn.com/w640/uy.png" },
  { "country": "South Korea", "code": "kr", "url": "https://flagcdn.com/w640/kr.png" }
]